challenge_rlcrt/__init__.py
challenge_rlcrt/__main__.py
challenge_rlcrt/application.py
challenge_rlcrt-1.0.0.dist-info/LICENSE
challenge_rlcrt-1.0.0.dist-info/METADATA
challenge_rlcrt-1.0.0.dist-info/WHEEL
challenge_rlcrt-1.0.0.dist-info/entry_points.txt
challenge_rlcrt-1.0.0.dist-info/top_level.txt
challenge_rlcrt-1.0.0.dist-info/RECORD
