Metadata-Version: 2.1
Name: challenge-rlcrt
Version: 1.0.0
Summary: An accepted challenge!
Home-page: https://gitlab.com/ricklacerte/challenge
Author: Rick Lacerte
Author-email: bliblabla@gmail.com
License: MIT
Platform: UNKNOWN
Classifier: Development Status :: 2 - Pre-Alpha
Classifier: License :: OSI Approved :: MIT License
Classifier: Programming Language :: Python
Classifier: Programming Language :: Python :: 3
Classifier: Programming Language :: Python :: 3.4
Classifier: Programming Language :: Python :: 3.5
Classifier: Programming Language :: Python :: 3.6
Classifier: Programming Language :: Python :: 3.7
Requires-Dist: Click
Requires-Dist: numpy
Requires-Dist: opencv-python
